gdaxtrader/__init__.py
gdaxtrader/admin.py
gdaxtrader/apps.py
gdaxtrader/common.py
gdaxtrader/models.py
gdaxtrader/tests.py
gdaxtrader/views.py
gdaxtrader-0.1a1.dist-info/DESCRIPTION.rst
gdaxtrader-0.1a1.dist-info/METADATA
gdaxtrader-0.1a1.dist-info/RECORD
gdaxtrader-0.1a1.dist-info/WHEEL
gdaxtrader-0.1a1.dist-info/metadata.json
gdaxtrader-0.1a1.dist-info/top_level.txt
