Metadata-Version: 2.0
Name: gdaxtrader
Version: 0.1a1
Summary: Automated and manual cryptocurrency trading on the GDAX exchange without fees
Home-page: http://github.com/bmbouter/gdaxtrader
Author: Brian Bouterse
Author-email: bmbouter@gmail.com
License: GPLv3
Platform: UNKNOWN
Classifier: Development Status :: 2 - Pre-Alpha
Classifier: Intended Audience :: Developers
Classifier: License :: OSI Approved :: GNU General Public License v3 (GPLv3)
Classifier: Natural Language :: English
Classifier: Programming Language :: Python :: 3
Classifier: Programming Language :: Python :: 3.5
Requires-Dist: django
Requires-Dist: gdax
